stanlogic/BoolMin2D.py
stanlogic/BoolMinGeo.py
stanlogic/BoolMinHcal.py
stanlogic/__init__.py
stanlogic/kmapsolver3D.py
stanlogic/ones_complement.py
stanlogic-2.1.0.dist-info/METADATA
stanlogic-2.1.0.dist-info/WHEEL
stanlogic-2.1.0.dist-info/top_level.txt
stanlogic-2.1.0.dist-info/RECORD
