Metadata-Version: 2.4
Name: stanlogic
Version: 2.1.0
Summary: A Boolean simplification and inference library that integrates K-Map simplification and logical inference.
Author: Stan's Technologies
Author-email: Somtochukwu Stanislus Emeka-Onwuneme <somtochukwueo@outlook.com>
License: Dual licensed: AGPL - 3.0, Commercial License
Keywords: boolean-algebra,kmap,logic-simplification,inference,symbolic-logic
Classifier: Programming Language :: Python :: 3
Classifier: License :: OSI Approved :: GNU Affero General Public License v3
Classifier: Operating System :: OS Independent
Requires-Python: >=3.8
Requires-Dist: matplotlib>=3.5.0
Requires-Dist: numpy>=1.21.0
Provides-Extra: web
Requires-Dist: Flask>=2.0; extra == "web"
Requires-Dist: Flask-Cors>=3.0; extra == "web"
Provides-Extra: dev
Requires-Dist: pytest>=7.0.0; extra == "dev"
Requires-Dist: pytest-cov>=3.0.0; extra == "dev"
Dynamic: author
Dynamic: requires-python
